learn2clean/__init__.py
learn2clean/classification/__init__.py
learn2clean/classification/classifier.py
learn2clean/clustering/__init__.py
learn2clean/clustering/clusterer.py
learn2clean/consistency_checking/__init__.py
learn2clean/consistency_checking/consistency_checker.py
learn2clean/duplicate_detection/__init__.py
learn2clean/duplicate_detection/duplicate_detector.py
learn2clean/feature_selection/__init__.py
learn2clean/feature_selection/feature_selector.py
learn2clean/imputation/__init__.py
learn2clean/imputation/imputer.py
learn2clean/loading/__init__.py
learn2clean/loading/reader.py
learn2clean/normalization/__init__.py
learn2clean/normalization/normalizer.py
learn2clean/outlier_detection/__init__.py
learn2clean/outlier_detection/outlier_detector.py
learn2clean/qlearning/__init__.py
learn2clean/qlearning/qlearner.py
learn2clean/regression/__init__.py
learn2clean/regression/regressor.py
learn2clean-0.2.1.dist-info/METADATA
learn2clean-0.2.1.dist-info/WHEEL
learn2clean-0.2.1.dist-info/top_level.txt
learn2clean-0.2.1.dist-info/RECORD
