Metadata-Version: 2.1
Name: learn2clean
Version: 0.2.1
Summary: Python Library for Data Preprocessing with Reinforcement Learning.
Home-page: https://github.com/LaureBerti/learn2clean
Author: Laure BERTI-EQUILLE
Author-email: laure.berti@ird.fr
License: BSD-3
Keywords: learn2clean data preprocessing pipeline
Platform: UNKNOWN
Classifier: Development Status :: 3 - Alpha
Classifier: Intended Audience :: Developers
Classifier: Intended Audience :: Science/Research
Classifier: Topic :: Scientific/Engineering :: Artificial Intelligence
Classifier: Topic :: Scientific/Engineering :: Information Analysis
Classifier: Topic :: Database
Classifier: Topic :: Software Development :: Libraries :: Python Modules
Classifier: License :: OSI Approved :: BSD License
Classifier: Natural Language :: English
Classifier: Operating System :: MacOS
Classifier: Programming Language :: Python :: 3.6
Requires-Dist: fancyimpute (==0.4.2)
Requires-Dist: impyute (==0.0.7)
Requires-Dist: jellyfish (==0.7.1)
Requires-Dist: joblib (==0.13.1)
Requires-Dist: matplotlib (==2.2.2)
Requires-Dist: numpy (==1.14.3)
Requires-Dist: pandas (==0.23.0)
Requires-Dist: py-stringmatching (==0.4.0)
Requires-Dist: py-stringsimjoin (==0.1.0)
Requires-Dist: scipy (==1.1.0)
Requires-Dist: seaborn (==0.8.1)
Requires-Dist: sklearn (==0.0)
Requires-Dist: sklearn-contrib-py-earth (==0.1.0)
Requires-Dist: statsmodels (==0.9.0)
Requires-Dist: tdda (==1.0.13)
